{"socialStatus":["Найманий працівник","Студент","Власна справа","Пенсіонер","Безробітний","Утриманець","Працює на себе неофіційно","Декретна відпустка","Державний службовець","Військовий"],"reasonForRetirement":["За віком","За вислугою років","За інвалідністю","По втраті годувальника","Багатодітним матерям та матерям інвалідів з дитинства"],"education":["Незакінчена середня","Середня","Середня - технічна","Незакінчена вища","Вища освіта","Науковий ступінь","Інше"],"typeOfEmployment":["На постійній основі","За тимчасовою угодою"],"typeOfJob":["Працюю за наймом по трудовій книжці","Працюю за наймом по договору","Працюю за наймом неофіційно","Пенсіонер працюючий","Пенсіонер непрацюючий","СПД (зареєстрований офіційно)","Ссамозайнята особа","Власник підприємства"],"levelPost":["Керівник вищої ланки","Керівник середньої ланки","Керівник нижчої ланки","Спеціаліст (але не керівник)","Службовець","Кваліфікований працівник","Некваліфікований працівник"],"ghroupDisability":["І","ІІ","ІІІ"],"formOfOwnership":["Повна властність","Часткова властність","Ввідомче","Орендоване","Гуртожиток","Проживаю у родичів","Проживаю у друзів","Проживаю у дружини/чоловіка"],"wage":["Немає документу","Довідка про доходи","Виписка з зарплатного рахунку​"],"creditHistory":["Не отримував раніше кредитів","Користувався та погасив","В даний час є непогашені кредити/незакриті кредитні картки"],"dontReceivedCredits":["Користувався та погасив","В даний час є непогашені кредити/незакриті кредитні картки"],"pension":["Немає документу","Довідка з пенсійної установи","Виписка з пенсійного рахунку"],"interestOnDeposits":["Немає документу","Виписка з рахунку щодо нарах. процентів"],"USACategory":["офіційні особи, які перебували в США на підставі віз категорій А і G","вчителі та тренери, які перебували в США на підставі віз категорії J і Q","студенти, які перебували в США на підставі віз категорій F, J, М, Q","спортсмени, що знаходилися в США для участі у благодійних спортивних змаганнях","Ви не відноситься ні до однієї, з перелічених вище категорій осіб"],"leasePayments":["Немає документу","Виписка з рахунку щодо орендних платежів","Акт щодо розрахунків за оренду","Декларація про доходи"],"ownershipOfCorporateRights":["Немає документу","Виписка з поточного рахунку","Декларація про доход"],"socialPayments":["Немає документу","Виписка з поточного рахунку","Квитанція"],"grossIncome":["Немає документу","Звіт платника єдиного податку","Декларація про доходи","Виписка з поточного рахунку"]}