[{"id":1,"defaultName":"Освіта","sort":1},{"id":2,"defaultName":"Автомобіль","sort":2},{"id":3,"defaultName":"Пенсія","sort":3},{"id":4,"defaultName":"Капітал","sort":4},{"id":5,"defaultName":"Фінансова стабільність","sort":5},{"id":6,"defaultName":"Відпустка","sort":6},{"id":7,"defaultName":"Матеріальні блага","sort":7},{"id":8,"defaultName":"Власна справа","sort":8},{"id":9,"defaultName":"Дача","sort":9},{"id":10,"defaultName":"Нерухомість","sort":10},{"id":11,"defaultName":"Заслужений відпочінок","sort":11},{"id":13,"defaultName":"Можливості дітям","sort":13},{"id":14,"defaultName":"Благодійнсіть","sort":15},{"id":15,"defaultName":"Діти","sort":16},{"id":16,"defaultName":"Cім'я","sort":17},{"id":17,"defaultName":"Віра в Бога","sort":18},{"id":18,"defaultName":"Здоров'я","sort":19},{"id":19,"defaultName":"Любов","sort":20},{"id":20,"defaultName":"Весілля","sort":14},{"id":21,"defaultName":"Інше","sort":14}]