[{"version":"1.2.0","dateRelease":" 11/08/16","log":[{"name":"Додана можливість проведення короткої презентації","type":"add"},{"name":"Додано слайд «Гроші вдома»","type":"add"},{"name":"Додано слайд «Цільова накопичувальна програма»","type":"add"},{"name":"Додано слайд «Інвестиційна програма»","type":"add"},{"name":"Додано слайд «Розрахунок можливої пенсії»","type":"add"},{"name":"В іконку інше додана можливість вносити назву цілі","type":"add"},{"name":"Виправлені критичні помилки","type":"bug"},{"name":"Інші зміни та покращення","type":"other"}]},{"version":"1.1.0","dateRelease":" 23/02/16","log":[{"name":"Додана комерційна пропозиція","type":"add"},{"name":"Додані розрахунки по цільовій програмі","type":"test"},{"name":"Додані іконки сім'ї, якщо клієнт старший 45 років","type":"add"},{"name":"Дадана нова ціль - «Інше»","type":"add"},{"name":"Додано поле «Накопичена сума» в опціях цілі","type":"add"},{"name":"Додана синхронізація між декількома пристроями","type":"add"},{"name":"Оновлені довідники автомобілей та квартир","type":"update"},{"name":"Виправлені критичні помилки","type":"bug"},{"name":"Інші зміни та покращення","type":"other"}]},{"version":"1.0.0","dateRelease":" 11/12/15","log":[{"name":"Initial release","type":"other"}]}]